{
  "topicCounts": {
    "DIFFM_013": 2,
    "DIFF1_020": 1
  },
  "topicQuestions": {
    "DIFFM_013": [
      {
        "paper": "2025年高等数学真题试卷 - 副本",
        "qid": "Q01",
        "snippet": "江苏省 2025 年普通高校 “ 专转本 ” 选拔考试 高等数学 试题卷 一、 单项选择题（本大题共 8 小题，每小题 4 分，共 32 分） 1.                x x b x a x x 2…",
        "fullText": "江苏省 2025 年普通高校 “ 专转本 ” 选拔考试 高等数学 试题卷 一、 单项选择题（本大题共 8 小题，每小题 4 分，共 32 分） 1.                x x b x a x x 2 lim （ ） A. b a e  B. a b e  C. b a e D. a b e 2. 设     x x f cos 1 cos 1    ，     x x g n n sin sin  ， 若当 0  x 时 ，   x f 与   x g 为同阶 无穷小，则正整数  n （ ） A. 1 B. 2 C. 3 D. 4 3. 设函数   x f 在 0 x 处可导，则         0 0 0 0 lim x x x xf x f x x x （ ） A.     0 0 0 x f x f x   B.     0 0 0 x f x x f   C.     0 0 0 x f x x f   D.     0 0 0 x f x f x   4. 曲线 1 1 sin   x x y 的渐近线方程为（ ） A. 0  x B. 0  y C. 1  x D. 1  y 5. 设     x dt t x x f 0 2 cos ，则      0 f （ ） A. 0 B. 1 C. 2 D. 3 6. 设 k 为常数，则级数       1 1 sin 1 n k n n 条件收敛的充分必要条件是（ ）\nA. 1 0   k B.    k 1 C. 2 0   k D.    k 2 7. 设 A , B 为同阶方阵，且 B A AB   ，则一定可逆的矩阵为（ ） A. E A  与 E B  B. E A  与 E B  C. E A  与 E B  D. E A  与 E B  8. 设向量组            1 0 1 1  ，            1 3 2 k  ，             1 1 3 k k  线性相关 ， 而向量组             1 1 2 1  ，             4 3 3 2  ，             0 5 3 k  线性无关，则常数  k （ ） A. 3  B. 1  C. 1 D. 3 二、填空题（本大题共 6 小题，每小题 4 分，共 24 分） 9. 若 0  x 是函数           0 sin 0 1 arctan x x kx x x x f 的可去间断点，则常数  k 10. 设函数   x x y cos 2   ，则   0 x dy 11. 设函数     3 2 2   x f x g ，其中   x f 是可导函数，若   2 3   f ，   16 3   g ， 则    3 f 12. 若 0  x 是函数     x e a x x f   （ 其中 a 为常数 ） 的极值点 ， 则曲线   x f y  的拐点坐 标为 13. 设 a ， b 为常数，且 0  a ，若幂级数       1 n n n b x n a 的收敛区间为   5 , 3  ， 则   b a 14. 设矩阵 X 满足方程                       4 9 5 2 3 1 3 5 1 2 X ，则  X 三、 计算题（本大题共 8 小题，每小题 8 分，共 64 分）"
      },
      {
        "paper": "2025年高等数学真题试卷 - 副本",
        "qid": "Q02",
        "snippet": "15. 求极限     1 1 1 ln lim 3 0 0       x dt t e x x x 16. 求不定积分    dx x x x 2 2 3 4 4 17. 求定积分    1 0 3 2 …",
        "fullText": "15. 求极限     1 1 1 ln lim 3 0 0       x dt t e x x x 16. 求不定积分    dx x x x 2 2 3 4 4 17. 求定积分    1 0 3 2 1 dx x x x 18. 求微分方程   x x y y x cos 1     满足初始条件   1 0  y 的特解 19. 已知   y x f z ,  是由方程 e yz xz e z    3 2 所确定的函数，求 0 0 2      y x y x z 20. 求二重积分     D dxdy y x x cos sin 2 ，其中 D 是由直线 x y   1 与 x y   1 及 x 轴所 围成的闭区域 21. 设 C B A , , 均为 4 阶方阵，满足 C AB  ，已知 3  A ，                8 5 5 4 2 4 2 3 2 3 1 2 1 0 1 1 C ，求 B 22. 已知非齐次线性方程组                        k kx x x x x x x x x x x x x x x x 4 3 2 1 4 3 2 1 4 3 2 1 4 3 2 1 7 3 1 4 4 3 2 0 4 2 1 3 （其中 k 为常数）有无穷多解，求其 通解 四、证明题（本题 10 分） 23. 设函数   x f 在闭区间   1 0 ， 上具有二阶导数，且   1 0  f ，   0 1  f ，证明： (1) 在开区间   1 , 0 内至少存在一点  ，使得   1     f ； (2) 在开区间   1 , 0 内至少存在一点  ，使得     1          f f 五、综合题（本大题共 2 小题，每小题 10 分，共 20 分） 24. 设 D 是由抛物线 2 x y  与   2 2   x y 及 x 轴所围成的平面图形，求： (1) D 的面积；\n(2) D 绕 x 轴旋转一周所形成的旋转体的体积； (3) D 绕 y 轴旋转一周所形成的旋转体的体积 25. 设二阶可导函数   x f 满足方程       0 2 2       x f x f x f ，且   1 lim 0   x x f x ，求     0 dx x f"
      }
    ],
    "DIFF1_020": [
      {
        "paper": "2025年高等数学真题试卷 - 副本",
        "qid": "Q02",
        "snippet": "15. 求极限     1 1 1 ln lim 3 0 0       x dt t e x x x 16. 求不定积分    dx x x x 2 2 3 4 4 17. 求定积分    1 0 3 2 …",
        "fullText": "15. 求极限     1 1 1 ln lim 3 0 0       x dt t e x x x 16. 求不定积分    dx x x x 2 2 3 4 4 17. 求定积分    1 0 3 2 1 dx x x x 18. 求微分方程   x x y y x cos 1     满足初始条件   1 0  y 的特解 19. 已知   y x f z ,  是由方程 e yz xz e z    3 2 所确定的函数，求 0 0 2      y x y x z 20. 求二重积分     D dxdy y x x cos sin 2 ，其中 D 是由直线 x y   1 与 x y   1 及 x 轴所 围成的闭区域 21. 设 C B A , , 均为 4 阶方阵，满足 C AB  ，已知 3  A ，                8 5 5 4 2 4 2 3 2 3 1 2 1 0 1 1 C ，求 B 22. 已知非齐次线性方程组                        k kx x x x x x x x x x x x x x x x 4 3 2 1 4 3 2 1 4 3 2 1 4 3 2 1 7 3 1 4 4 3 2 0 4 2 1 3 （其中 k 为常数）有无穷多解，求其 通解 四、证明题（本题 10 分） 23. 设函数   x f 在闭区间   1 0 ， 上具有二阶导数，且   1 0  f ，   0 1  f ，证明： (1) 在开区间   1 , 0 内至少存在一点  ，使得   1     f ； (2) 在开区间   1 , 0 内至少存在一点  ，使得     1          f f 五、综合题（本大题共 2 小题，每小题 10 分，共 20 分） 24. 设 D 是由抛物线 2 x y  与   2 2   x y 及 x 轴所围成的平面图形，求： (1) D 的面积；\n(2) D 绕 x 轴旋转一周所形成的旋转体的体积； (3) D 绕 y 轴旋转一周所形成的旋转体的体积 25. 设二阶可导函数   x f 满足方程       0 2 2       x f x f x f ，且   1 lim 0   x x f x ，求     0 dx x f"
      }
    ]
  },
  "questionCount": 2,
  "updatedAt": 1777100581753
}