{
  "topicCounts": {
    "LIM_023": 1,
    "DIFF1_020": 1,
    "DIFFM_013": 1
  },
  "topicQuestions": {
    "LIM_023": [
      {
        "paper": "2015年高等数学真题试卷",
        "qid": "Q01",
        "snippet": "江苏省 2015 年普通高校专转本统一考试 高等数学 试卷 一、选择题 1. 当 0 x  时，函数   sin 1 x f x e   时函数   g x x  的（ ) A. 高阶无穷小 B. 低阶无穷小 C. 同阶无穷…",
        "fullText": "江苏省 2015 年普通高校专转本统一考试 高等数学 试卷 一、选择题 1. 当 0 x  时，函数   sin 1 x f x e   时函数   g x x  的（ ) A. 高阶无穷小 B. 低阶无穷小 C. 同阶无穷小 D. 等价无穷小 2. 函数   1 x y x   （ 1 x  ）的微分 dy 为（ ） A.     1 ln 1 1 x x x x dx x           B.     1 ln 1 1 x x x x dx x           C.   1 1 x x x dx   D.   1 1 x x x dx    3. 0 x  是函数   1 1 1 1 0 1 0 x x e x f x e x             的（ ） A. 无穷间断点 B. 跳跃间断点 C. 可去间断点 D. 连续点 4. 设   F x 是函数   f x 的一个原函数，则   3 2 f x dx    （ ） A.   1 3 2 2 F x c    B.   1 3 2 2 F x c   C.   2 3 2 F x c    D.   2 3 2 F x c   5. 下列级数条件收敛的是（ ） A.   2 1 1 n n n n      B.   1 1 1 2 1 n n n n       C.   1 ! 1 n n n n n     D.   2 1 1 1 n n n n      6. 二次积分   1 1 ln , e y dy f x y dx    （ ） A.   1 1 ln , e x dx f x y dy   B.   1 1 0 , x e dx f x y dy   C.   1 0 0 , x e dx f x y dy   D.   1 0 1 , x e dx f x y dy  "
      },
      {
        "paper": "2015年高等数学真题试卷",
        "qid": "Q02",
        "snippet": "二、填空题 7. 设   lim 1 n n x f x n          ，则   ln 2 f  8. 曲线 2 3 2 1 1 x t t y t         在点   0, …",
        "fullText": "二、填空题 7. 设   lim 1 n n x f x n          ，则   ln 2 f  8. 曲线 2 3 2 1 1 x t t y t         在点   0, 2 处的切线方程为 9. 略（不在新大纲范围内） 10. 设   1 2 1 f x x   ，则     n f x  11. 微分方程 2 ' xy y x   满足初始条件 1 2 x y   的特解为 12. 幂级数   1 2 1 n n n x n     的收敛域为 三、计算题 13. 求极限 0 2 0 arcsin lim 2 2 2 x x x t tdt e x x      14. 设   2 sin 0 0 0 x x x f x x x          ，求   ' f x 15. 略（不在新大纲范围内） 16. 求不定积分 3 2 9 x dx x   17. 计算定积分   2 2 2 sin x x xdx      18. 设   , x z f x y         ， 其中函数 f 有二阶连续偏导数 ， 函数  具有连续导数 ， 求 2 z x y    19. 计算二重积分 D xydxdy  ，其中 D 为由曲线 2 4 y x   与直线 y x  及直线 2 y  所 围成的平面闭区域"
      }
    ],
    "DIFF1_020": [
      {
        "paper": "2015年高等数学真题试卷",
        "qid": "Q01",
        "snippet": "江苏省 2015 年普通高校专转本统一考试 高等数学 试卷 一、选择题 1. 当 0 x  时，函数   sin 1 x f x e   时函数   g x x  的（ ) A. 高阶无穷小 B. 低阶无穷小 C. 同阶无穷…",
        "fullText": "江苏省 2015 年普通高校专转本统一考试 高等数学 试卷 一、选择题 1. 当 0 x  时，函数   sin 1 x f x e   时函数   g x x  的（ ) A. 高阶无穷小 B. 低阶无穷小 C. 同阶无穷小 D. 等价无穷小 2. 函数   1 x y x   （ 1 x  ）的微分 dy 为（ ） A.     1 ln 1 1 x x x x dx x           B.     1 ln 1 1 x x x x dx x           C.   1 1 x x x dx   D.   1 1 x x x dx    3. 0 x  是函数   1 1 1 1 0 1 0 x x e x f x e x             的（ ） A. 无穷间断点 B. 跳跃间断点 C. 可去间断点 D. 连续点 4. 设   F x 是函数   f x 的一个原函数，则   3 2 f x dx    （ ） A.   1 3 2 2 F x c    B.   1 3 2 2 F x c   C.   2 3 2 F x c    D.   2 3 2 F x c   5. 下列级数条件收敛的是（ ） A.   2 1 1 n n n n      B.   1 1 1 2 1 n n n n       C.   1 ! 1 n n n n n     D.   2 1 1 1 n n n n      6. 二次积分   1 1 ln , e y dy f x y dx    （ ） A.   1 1 ln , e x dx f x y dy   B.   1 1 0 , x e dx f x y dy   C.   1 0 0 , x e dx f x y dy   D.   1 0 1 , x e dx f x y dy  "
      },
      {
        "paper": "2015年高等数学真题试卷",
        "qid": "Q02",
        "snippet": "二、填空题 7. 设   lim 1 n n x f x n          ，则   ln 2 f  8. 曲线 2 3 2 1 1 x t t y t         在点   0, …",
        "fullText": "二、填空题 7. 设   lim 1 n n x f x n          ，则   ln 2 f  8. 曲线 2 3 2 1 1 x t t y t         在点   0, 2 处的切线方程为 9. 略（不在新大纲范围内） 10. 设   1 2 1 f x x   ，则     n f x  11. 微分方程 2 ' xy y x   满足初始条件 1 2 x y   的特解为 12. 幂级数   1 2 1 n n n x n     的收敛域为 三、计算题 13. 求极限 0 2 0 arcsin lim 2 2 2 x x x t tdt e x x      14. 设   2 sin 0 0 0 x x x f x x x          ，求   ' f x 15. 略（不在新大纲范围内） 16. 求不定积分 3 2 9 x dx x   17. 计算定积分   2 2 2 sin x x xdx      18. 设   , x z f x y         ， 其中函数 f 有二阶连续偏导数 ， 函数  具有连续导数 ， 求 2 z x y    19. 计算二重积分 D xydxdy  ，其中 D 为由曲线 2 4 y x   与直线 y x  及直线 2 y  所 围成的平面闭区域"
      },
      {
        "paper": "2015年高等数学真题试卷",
        "qid": "Q03",
        "snippet": "20. 已知 2 3 1 2 x x x y c e c e xe    是二阶常系数非齐次线性微分方程   '' ' y py qy f x    的 通解，试求该微分方程 四、综合题 21. 设 D 是由曲线 2 y x…",
        "fullText": "20. 已知 2 3 1 2 x x x y c e c e xe    是二阶常系数非齐次线性微分方程   '' ' y py qy f x    的 通解，试求该微分方程 四、综合题 21. 设 D 是由曲线 2 y x  与直线 y ax  （ 0 a  ）所围成的平面图形，已知 D 分别绕两坐 标轴旋转一周所形成的旋转体的体积相等，试求： (1) 常数 a 的值 (2) 平面图形 D 的面积 22. 设函数     2 1 ax b f x x    在点 1 x  处取得极值 1 4  ，试求 (1) 常数 , a b 的值 (2) 曲线   y f x  的凹凸区间与拐点 (3) 曲线   y f x  的渐近线 五、证明题 23. 证明：当 0 1 x   时，     2 ln 1 2 x x x    24. 设   , z z x y  是由方程   2 2 y z xf y z    所确定的函数 ， 其中 f 为可导函数 ， 证明 ： z z x z y x y      "
      }
    ],
    "DIFFM_013": [
      {
        "paper": "2015年高等数学真题试卷",
        "qid": "Q03",
        "snippet": "20. 已知 2 3 1 2 x x x y c e c e xe    是二阶常系数非齐次线性微分方程   '' ' y py qy f x    的 通解，试求该微分方程 四、综合题 21. 设 D 是由曲线 2 y x…",
        "fullText": "20. 已知 2 3 1 2 x x x y c e c e xe    是二阶常系数非齐次线性微分方程   '' ' y py qy f x    的 通解，试求该微分方程 四、综合题 21. 设 D 是由曲线 2 y x  与直线 y ax  （ 0 a  ）所围成的平面图形，已知 D 分别绕两坐 标轴旋转一周所形成的旋转体的体积相等，试求： (1) 常数 a 的值 (2) 平面图形 D 的面积 22. 设函数     2 1 ax b f x x    在点 1 x  处取得极值 1 4  ，试求 (1) 常数 , a b 的值 (2) 曲线   y f x  的凹凸区间与拐点 (3) 曲线   y f x  的渐近线 五、证明题 23. 证明：当 0 1 x   时，     2 ln 1 2 x x x    24. 设   , z z x y  是由方程   2 2 y z xf y z    所确定的函数 ， 其中 f 为可导函数 ， 证明 ： z z x z y x y      "
      }
    ]
  },
  "questionCount": 3,
  "updatedAt": 1777100491457
}