{
  "topicCounts": {
    "LIM_022": 1,
    "DIFF1_020": 1
  },
  "topicQuestions": {
    "LIM_022": [
      {
        "paper": "2023年高等数学真题试卷 - 副本",
        "qid": "Q01",
        "snippet": "江苏省专转本 2023 届高等数学真题试卷 一、选择题（本大题共 8 小题，每小题 4 分，共 32 分） 1. 若 1 x  是函数   2 x ax b f x x a     的第一类间断点，则 ab  （ ） A. …",
        "fullText": "江苏省专转本 2023 届高等数学真题试卷 一、选择题（本大题共 8 小题，每小题 4 分，共 32 分） 1. 若 1 x  是函数   2 x ax b f x x a     的第一类间断点，则 ab  （ ） A. 2  B. 1  C. 1 D. 2 2. 设函数   1 x e f x x   ， 若当 0 x  时 ，     0 lim x f x f x   是 k ax 的等价无穷小 ， 则 , a k 的值依次为（ ） A. 2,1 B. 1, 2 C. 1 ,1 2 D. 1 , 2 2 3. 设函数   y f x  的微分为 1 1 dy dx x   ，则     2023 0 f  （ ） A. 2022!  B. 2022! C. 2023!  D. 2023! 4. 若函数   f x 的一个原函数为 sin 2 x ，则   ' 1 f  （ ） A. 2 cos 2 B. 1 cos 2 2  C. 2sin 2  D. 4sin 2  5. 设二元函数   , f u v 具有连续偏导数 ， 且满足   2 2 , f x y x y x y     ， 则   ' 2, 0 u f 与   ' 2, 0 v f 依次为（ ） A. 2, 2  B. 2, 2 C. 0, 2 D. 4, 0 6. 若级数   1 1 n p n n     收敛，而级数 1 1 n n p    发散，则（ ） A. 0 1 p   B. 0 1 p   C. 1 p  D. 1 p  7. 设 1 1 1 1 1 1 a A a a            ，若 A 的秩为 2 ，则 a  （ ） A. 2  B. 1  C. 0 D. 1 8. 若向量组 1 2 3 , ,    线性无关， k 为非零常数，则向量组 1 2 2 3 3 1 , , k k k          ，\n线性相关的充分必要条件为（ ） A. 1 k  B. 1 k   C. 1 k  D. 1 k   二、填空题（本大题共 6 小题，每小题 4 分，共 24 分） 9. 设     0 1 1 sin sin 2 lim x f x x x f x x x     ，则   0 lim x f x   10. 设直线 3 y x m   是曲线 2 2 1 1 x t t y t t          的一条切线，则 m  11. 设   f x 是可导的奇函数，且 2 lim 1 n nf n         ，则   ' 0 f  12. 设 3 1 1 1 x y dt t    ，则 1 x dx dy   13. 若幂级数   1 1 n n n x na     的收敛域为   3,1  ，则常数 a  14. 设 , A B 均为 3 阶方阵，且 4 A  ， 2 1 0 1 3 0 0 0 4 AB            ，则 B  三、计算题（本大题共 8 小题，每小题 8 分，共 64 分） 15. 求极限 2 2 0 sin 2 cos 2 lim cos x x x x x x x     16. 已知   2 arctan xf x dx x x c    ，求   f x dx  17. 计算定积分 2 2 2 0 4 x dx x   18. 设   , z z x y  是由方程 3 3 6 1 z xz y    所确定的函数，求 2 0 0 x y z x y      19. 已知 x y xe  为微分方程 '' ' x y py qy e     的一个特解，求微分方程满足初始条件 0 1 x y   ， 0 ' 2 x y   的特解"
      },
      {
        "paper": "2023年高等数学真题试卷 - 副本",
        "qid": "Q02",
        "snippet": "20. 计算二重积分   2 cos D y x dxdy   ，其中 D 是由曲线 cos 0 2 y x x           与两直线 , 1 2 x y    所围成的平面闭区域 21. 设 0…",
        "fullText": "20. 计算二重积分   2 cos D y x dxdy   ，其中 D 是由曲线 cos 0 2 y x x           与两直线 , 1 2 x y    所围成的平面闭区域 21. 设 0 1 1 2 2 2 1 1 1 A               ，求矩阵 X ，使得 AX A X   22. 问  取何值时，线性方程组 1 2 1 2 3 2 1 2 3 2 1 2 3 1 x x x x x x x x                 有解，并求其解 四、证明题（本大题共 10 分） 23. 证明：当 0 x  时， 2 sin cos 1 x x x x     五、综合题（本大题共 2 小题，每小题 10 分，共 20 分） 24. 设函数   2 2 2 1 1 ax x f x x bx      ， 已知直线 1 x  与 0 y  均为曲线   y f x  的渐近线 ， 求 ： (1) 常数 , a b 的值 (2) 曲线   y f x  的凹凸区间与拐点 25. 设   f x 是定义在   ,   上的正值连续函数 ， 且   0 1 f  ， D 为由曲线   y f x  与 直线 0 x  ，   0 x t t   及 x 轴所围成的曲边梯形， D 的面积记为   A t ， D 绕 y 轴旋转 所形成的旋转体体积记为   V t ，已知     1 1 2 2 A t f t   ，求   lim t V t "
      }
    ],
    "DIFF1_020": [
      {
        "paper": "2023年高等数学真题试卷 - 副本",
        "qid": "Q01",
        "snippet": "江苏省专转本 2023 届高等数学真题试卷 一、选择题（本大题共 8 小题，每小题 4 分，共 32 分） 1. 若 1 x  是函数   2 x ax b f x x a     的第一类间断点，则 ab  （ ） A. …",
        "fullText": "江苏省专转本 2023 届高等数学真题试卷 一、选择题（本大题共 8 小题，每小题 4 分，共 32 分） 1. 若 1 x  是函数   2 x ax b f x x a     的第一类间断点，则 ab  （ ） A. 2  B. 1  C. 1 D. 2 2. 设函数   1 x e f x x   ， 若当 0 x  时 ，     0 lim x f x f x   是 k ax 的等价无穷小 ， 则 , a k 的值依次为（ ） A. 2,1 B. 1, 2 C. 1 ,1 2 D. 1 , 2 2 3. 设函数   y f x  的微分为 1 1 dy dx x   ，则     2023 0 f  （ ） A. 2022!  B. 2022! C. 2023!  D. 2023! 4. 若函数   f x 的一个原函数为 sin 2 x ，则   ' 1 f  （ ） A. 2 cos 2 B. 1 cos 2 2  C. 2sin 2  D. 4sin 2  5. 设二元函数   , f u v 具有连续偏导数 ， 且满足   2 2 , f x y x y x y     ， 则   ' 2, 0 u f 与   ' 2, 0 v f 依次为（ ） A. 2, 2  B. 2, 2 C. 0, 2 D. 4, 0 6. 若级数   1 1 n p n n     收敛，而级数 1 1 n n p    发散，则（ ） A. 0 1 p   B. 0 1 p   C. 1 p  D. 1 p  7. 设 1 1 1 1 1 1 a A a a            ，若 A 的秩为 2 ，则 a  （ ） A. 2  B. 1  C. 0 D. 1 8. 若向量组 1 2 3 , ,    线性无关， k 为非零常数，则向量组 1 2 2 3 3 1 , , k k k          ，\n线性相关的充分必要条件为（ ） A. 1 k  B. 1 k   C. 1 k  D. 1 k   二、填空题（本大题共 6 小题，每小题 4 分，共 24 分） 9. 设     0 1 1 sin sin 2 lim x f x x x f x x x     ，则   0 lim x f x   10. 设直线 3 y x m   是曲线 2 2 1 1 x t t y t t          的一条切线，则 m  11. 设   f x 是可导的奇函数，且 2 lim 1 n nf n         ，则   ' 0 f  12. 设 3 1 1 1 x y dt t    ，则 1 x dx dy   13. 若幂级数   1 1 n n n x na     的收敛域为   3,1  ，则常数 a  14. 设 , A B 均为 3 阶方阵，且 4 A  ， 2 1 0 1 3 0 0 0 4 AB            ，则 B  三、计算题（本大题共 8 小题，每小题 8 分，共 64 分） 15. 求极限 2 2 0 sin 2 cos 2 lim cos x x x x x x x     16. 已知   2 arctan xf x dx x x c    ，求   f x dx  17. 计算定积分 2 2 2 0 4 x dx x   18. 设   , z z x y  是由方程 3 3 6 1 z xz y    所确定的函数，求 2 0 0 x y z x y      19. 已知 x y xe  为微分方程 '' ' x y py qy e     的一个特解，求微分方程满足初始条件 0 1 x y   ， 0 ' 2 x y   的特解"
      },
      {
        "paper": "2023年高等数学真题试卷 - 副本",
        "qid": "Q02",
        "snippet": "20. 计算二重积分   2 cos D y x dxdy   ，其中 D 是由曲线 cos 0 2 y x x           与两直线 , 1 2 x y    所围成的平面闭区域 21. 设 0…",
        "fullText": "20. 计算二重积分   2 cos D y x dxdy   ，其中 D 是由曲线 cos 0 2 y x x           与两直线 , 1 2 x y    所围成的平面闭区域 21. 设 0 1 1 2 2 2 1 1 1 A               ，求矩阵 X ，使得 AX A X   22. 问  取何值时，线性方程组 1 2 1 2 3 2 1 2 3 2 1 2 3 1 x x x x x x x x                 有解，并求其解 四、证明题（本大题共 10 分） 23. 证明：当 0 x  时， 2 sin cos 1 x x x x     五、综合题（本大题共 2 小题，每小题 10 分，共 20 分） 24. 设函数   2 2 2 1 1 ax x f x x bx      ， 已知直线 1 x  与 0 y  均为曲线   y f x  的渐近线 ， 求 ： (1) 常数 , a b 的值 (2) 曲线   y f x  的凹凸区间与拐点 25. 设   f x 是定义在   ,   上的正值连续函数 ， 且   0 1 f  ， D 为由曲线   y f x  与 直线 0 x  ，   0 x t t   及 x 轴所围成的曲边梯形， D 的面积记为   A t ， D 绕 y 轴旋转 所形成的旋转体体积记为   V t ，已知     1 1 2 2 A t f t   ，求   lim t V t "
      }
    ]
  },
  "questionCount": 2,
  "updatedAt": 1777100512992
}